sense_hat_matrix/Graph.py
sense_hat_matrix/GraphUtil.py
sense_hat_matrix/LedMatrix.py
sense_hat_matrix/LedMatrixUtil.py
sense_hat_matrix/__init__.py
sense_hat_matrix/app.py
test/DoesItWork.py
test/PrettyPrint.py
test/TestGraph.py
test/TestGraphUtil.py
test/TestLedMatrixUtil.py
test/__init__.py
sense_hat_matrix-0.0.8.dist-info/LICENSE
sense_hat_matrix-0.0.8.dist-info/METADATA
sense_hat_matrix-0.0.8.dist-info/WHEEL
sense_hat_matrix-0.0.8.dist-info/top_level.txt
sense_hat_matrix-0.0.8.dist-info/RECORD
