Metadata-Version: 2.1
Name: sense-hat-matrix
Version: 0.0.8
Summary: Manipulate the LED matrix of the sense-hat
Home-page: https://github.com/szigyi/sense-hat-matrix
Project-URL: Bug Tracker, https://github.com/szigyi/sense-hat-matrix/issues
Project-URL: Changelog, https://github.com/szigyi/sense-hat-matrix/releases
Classifier: Programming Language :: Python :: 3
Classifier: License :: OSI Approved :: BSD License
Classifier: Intended Audience :: Developers
Requires-Python: >=3.6
License-File: LICENSE
Requires-Dist: numpy (>=1.16.0)
